LICENSE
MANIFEST.in
README.rst
requirements.txt
setup.py
pysqes/__init__.py
pysqes/conn.py
pysqes/queue.py
pysqes/task.py
pysqes/utils.py
pysqes/worker.py
pysqes.egg-info/PKG-INFO
pysqes.egg-info/SOURCES.txt
pysqes.egg-info/dependency_links.txt
pysqes.egg-info/entry_points.txt
pysqes.egg-info/requires.txt
pysqes.egg-info/top_level.txt
pysqes/bin/__init__.py
pysqes/bin/base.py
pysqes/bin/pysqes.py
pysqes/bin/worker.py
pysqes/runners/__init__.py
pysqes/runners/gevent_runner.py
pysqes/runners/process_runner.py