Metadata-Version: 1.1
Name: pysqes
Version: 0.2.1
Summary: A simple queue service using Amazon SQS and boto
Home-page: https://github.com/sauramirez/pysqes
Author: Essau Ramirez
Author-email: saumotions+pypi@gmail.com
License: Apache
Download-URL: https://github.com/sauramirez/pysqes
Keywords: queue,amazon,distributed
Platform: UNKNOWN
